.pylintrc
AUTHORS
FAQ
INSTALL
LICENSE
MANIFEST.in
NEWS
README
THANKS
TODO
build.vel
make_api_docs.sh
setup.cfg
setup.py
doapfiend/__init__.py
doapfiend/cli.py
doapfiend/doap2html.xsl
doapfiend/doaplib.py
doapfiend/lexers.py
doapfiend/model.py
doapfiend/utils.py
doapfiend.egg-info/PKG-INFO
doapfiend.egg-info/SOURCES.txt
doapfiend.egg-info/dependency_links.txt
doapfiend.egg-info/entry_points.txt
doapfiend.egg-info/not-zip-safe
doapfiend.egg-info/requires.txt
doapfiend.egg-info/top_level.txt
doapfiend/plugins/__init__.py
doapfiend/plugins/base.py
doapfiend/plugins/fields.py
doapfiend/plugins/freshmeat.py
doapfiend/plugins/homepage.py
doapfiend/plugins/n3.py
doapfiend/plugins/ohloh.py
doapfiend/plugins/pkg_index.py
doapfiend/plugins/pypi.py
doapfiend/plugins/sourceforge.py
doapfiend/plugins/text.py
doapfiend/plugins/url.py
doapfiend/plugins/xml.py
docs/usage.txt
docs/api/api-objects.txt
docs/api/class-tree.html
docs/api/crarr.png
docs/api/doapfiend-module.html
docs/api/doapfiend-pysrc.html
docs/api/doapfiend.cli-module.html
docs/api/doapfiend.cli-pysrc.html
docs/api/doapfiend.cli.DoapFiend-class.html
docs/api/doapfiend.doaplib-module.html
docs/api/doapfiend.doaplib-pysrc.html
docs/api/doapfiend.lexers-module.html
docs/api/doapfiend.lexers-pysrc.html
docs/api/doapfiend.lexers.Notation3Lexer-class.html
docs/api/doapfiend.lexers.SparqlLexer-class.html
docs/api/doapfiend.model-module.html
docs/api/doapfiend.model-pysrc.html
docs/api/doapfiend.model.CVSRepository-class.html
docs/api/doapfiend.model.Project-class.html
docs/api/doapfiend.model.Release-class.html
docs/api/doapfiend.model.SVNRepository-class.html
docs/api/doapfiend.plugins-module.html
docs/api/doapfiend.plugins-pysrc.html
docs/api/doapfiend.plugins.base-module.html
docs/api/doapfiend.plugins.base-pysrc.html
docs/api/doapfiend.plugins.base.Plugin-class.html
docs/api/doapfiend.plugins.fields-module.html
docs/api/doapfiend.plugins.fields-pysrc.html
docs/api/doapfiend.plugins.fields.OutputPlugin-class.html
docs/api/doapfiend.plugins.freshmeat-module.html
docs/api/doapfiend.plugins.freshmeat-pysrc.html
docs/api/doapfiend.plugins.freshmeat.FreshmeatPlugin-class.html
docs/api/doapfiend.plugins.homepage-module.html
