Metadata-Version: 1.0
Name: doapfiend
Version: 0.3.3
Summary: Command-line tool and library for DOAP (Description of a Project) RDF.
Home-page: http://trac.doapspace.org/doapfiend
Author: Rob Cakebread
Author-email: <rob@doapspace.org>
License: BSD-2
Download-URL: http://doapspace.org/static/doapfiend/dist/doapfiend-0.3.3.tar.gz
Keywords: doap rdf semantic web
Platform: UNKNOWN
Classifier: Development Status :: 2 - Pre-Alpha
Classifier: Intended Audience :: Developers
Classifier: Intended Audience :: End Users/Desktop
Classifier: License :: OSI Approved :: BSD License
Classifier: Programming Language :: Python
Classifier: Topic :: Software Development :: Libraries :: Python Modules
